bdfparse/__init__.py
bdfparse/bdfparse.py
bdfparse/note.py
bdfparse-2019.8.dist-info/LICENSE
bdfparse-2019.8.dist-info/METADATA
bdfparse-2019.8.dist-info/WHEEL
bdfparse-2019.8.dist-info/top_level.txt
bdfparse-2019.8.dist-info/RECORD
