Metadata-Version: 2.1
Name: bdfparse
Version: 2019.8
Summary: A package for reading .bdf files into NumPy arrays.
Home-page: https://gitlab.com/MisterBiggs/bdfparse
Author: Anson Biggs
Author-email: anson@ansonbiggs.com
License: UNKNOWN
Platform: UNKNOWN
Classifier: Programming Language :: Python :: 3.7
Classifier: License :: OSI Approved :: MIT License
Classifier: Operating System :: OS Independent
